<?xml version='1.0' encoding='UTF-8'?>
<object id="3c2diVFQqxwd" classes="specific-data" acceptedChildren=":Proteus-none" acceptedParents="information-requirement">
  <properties>
    <stringProperty name=":Proteus-name" category="general"><![CDATA[Fecha de Devolución]]></stringProperty>
    <markdownProperty name="description" category="general"><![CDATA[Momento en que se procesó la devolución.]]></markdownProperty>
    <markdownProperty name="comments" category="comments"><![CDATA[]]></markdownProperty>
  </properties>
  <children/>
</object>
